diamant/__init__.py
diamant/py.typed
diamant-0.0.0.dist-info/WHEEL
diamant-0.0.0.dist-info/METADATA
diamant-0.0.0.dist-info/RECORD
