Metadata-Version: 2.1
Name: diamant
Version: 0.0.0
Summary: A Python implementation of the board game Diamant 💎
Home-page: https://MarkusShepherd.github.io/diamant
License: MIT
Author: Markus Shepherd
Author-email: markus@recommend.games
Requires-Python: >=3.7.1,<4.0
Classifier: Development Status :: 4 - Beta
Classifier: Intended Audience :: Developers
Classifier: License :: OSI Approved :: MIT License
Classifier: Operating System :: OS Independent
Classifier: Programming Language :: Python
Classifier: Programming Language :: Python :: 3
Classifier: Programming Language :: Python :: 3.10
Classifier: Programming Language :: Python :: 3.7
Classifier: Programming Language :: Python :: 3.8
Classifier: Programming Language :: Python :: 3.9
Classifier: Topic :: Software Development :: Libraries :: Python Modules
Classifier: Typing :: Typed
Project-URL: Documentation, https://MarkusShepherd.github.io/diamant
Project-URL: Repository, https://github.com/MarkusShepherd/diamant
